logisticpca/__init__.py
logisticpca/logistic_pca.py
logisticpca/ppca.py
logisticpca/setup.py
logisticpca-0.2.7.dist-info/licenses/LICENSE
logisticpca-0.2.7.dist-info/METADATA
logisticpca-0.2.7.dist-info/WHEEL
logisticpca-0.2.7.dist-info/top_level.txt
logisticpca-0.2.7.dist-info/RECORD
