Metadata-Version: 2.4
Name: logisticpca
Version: 0.2.7
Summary: A Python implementation of Logistic PCA, and its iterations.
Home-page: https://github.com/azaidr/logisticpca
Author: Reda Abouzaid
Author-email: azaidr00@gmail.com
Classifier: Programming Language :: Python :: 3
Classifier: License :: OSI Approved :: MIT License
Classifier: Operating System :: OS Independent
Requires-Python: >=3.6
License-File: LICENSE
Requires-Dist: torch
Requires-Dist: numpy
Dynamic: author
Dynamic: author-email
Dynamic: classifier
Dynamic: description-content-type
Dynamic: home-page
Dynamic: license-file
Dynamic: requires-dist
Dynamic: requires-python
Dynamic: summary
